nearup-1.16.0.data/scripts/nearup
nearup-1.16.0.data/scripts/watcher
nearuplib/VERSION
nearuplib/__init__.py
nearuplib/constants.py
nearuplib/exceptions.py
nearuplib/localnet.py
nearuplib/nodelib.py
nearuplib/tailer.py
nearuplib/util.py
nearuplib/watcher.py
tests/__init__.py
tests/test_download_binaries.py
tests/test_example.py
tests/test_exceptions.py
tests/test_key_generation.py
tests/test_logrotate.py
tests/test_metadata_reads.py
tests/test_nearup_integration_test.py
tests/test_nodelib.py
tests/test_watcher.py
nearup-1.16.0.dist-info/METADATA
nearup-1.16.0.dist-info/WHEEL
nearup-1.16.0.dist-info/top_level.txt
nearup-1.16.0.dist-info/RECORD
