Metadata-Version: 2.1
Name: nearup
Version: 1.16.0
Summary: Public scripts to launch near blockchain nodes
Home-page: https://github.com/near/nearup
Author: Near Inc
Author-email: hello@near.org
Classifier: Programming Language :: Python :: 3
Classifier: Development Status :: 3 - Alpha
Classifier: Intended Audience :: Developers
Classifier: Intended Audience :: System Administrators
Classifier: License :: OSI Approved :: BSD License
Classifier: Operating System :: MacOS :: MacOS X
Classifier: Operating System :: POSIX :: Linux
Classifier: Topic :: System :: Clustering
Classifier: Topic :: System :: Distributed Computing
Classifier: Topic :: System :: Installation/Setup
Classifier: Topic :: System :: Systems Administration
Classifier: Topic :: System :: Networking
Requires-Python: >=3.6
Requires-Dist: boto3
Requires-Dist: click
Requires-Dist: psutil
